RISC-V-Team16/mux.sv
module mux #(
    DATA_WIDTH = 32,
    OFFSET = 4
) (
    input   logic [DATA_WIDTH-1:0]  PC,
    input   logic [DATA_WIDTH-1:0]  ImmOp,
    input   logic                   PCsrc,
    output  logic [DATA_WIDTH-1:0]  next_PC
);
    
    logic [DATA_WIDTH-1:0] branch_PC;
    logic [DATA_WIDTH-1:0] inc_PC;

    always_comb begin
    branch_PC = PC + OFFSET;
    inc_PC = PC + ImmOp;
    end

    assign next_PC = PCsrc ? inc_PC : branch_PC;

endmodule

main/PCReg.sv
module PCReg #(
    DATA_WIDTH = 32
) (
    input   logic [DATA_WIDTH-1:0]  next_PC,
    input   logic                   clk,
    input   logic                   rst,
    output  logic [DATA_WIDTH-1:0]  PC
);

    always_ff @ (posedge clk, posedge rst)
        if (rst)
            PC <= 32'b0;
        else
            PC <= next_PC;

endmodule

RISC-V-Team16/top.sv
module top #(
    parameter DATA_WIDTH = 32
) (
    input   logic                  clk,
    input   logic                  rst,
    input   logic                  PCsrc,
    input   logic [DATA_WIDTH-1:0] ImmOp,
    output  logic [DATA_WIDTH-1:0] a0    
);

    logic [DATA_WIDTH-1:0] next_PC;
    logic [DATA_WIDTH-1:0] PC;

    assign a0 = PC;

    PCReg PCReg (
        .clk (clk),      
        .rst (rst),    
        .PC (PC),       
        .next_PC (next_PC)     	
    );

    mux mux (
        .PC (PC),     
        .ImmOp (ImmOp),      
        .PCsrc (PCsrc),       
        .next_PC (next_PC)     	
    );

endmodule

RISC-V-Team16/waveform.vcd
$version Generated by VerilatedVcd $end
$date Thu Nov 14 20:30:53 2024 $end
$timescale 1ps $end

 $scope module TOP $end
  $var wire 32 & ImmOp [31:0] $end
  $var wire  1 % PCsrc $end
  $var wire 32 ' a0 [31:0] $end
  $var wire  1 # clk $end
  $var wire  1 $ rst $end
  $scope module top $end
   $var wire 32 , DATA_WIDTH [31:0] $end
   $var wire 32 & ImmOp [31:0] $end
   $var wire 32 ) PC [31:0] $end
   $var wire  1 % PCsrc $end
   $var wire 32 ' a0 [31:0] $end
   $var wire  1 # clk $end
   $var wire 32 ( next_PC [31:0] $end
   $var wire  1 $ rst $end
   $scope module PCReg $end
    $var wire 32 , DATA_WIDTH [31:0] $end
    $var wire 32 ) PC [31:0] $end
    $var wire  1 # clk $end
    $var wire 32 ( next_PC [31:0] $end
    $var wire  1 $ rst $end
   $upscope $end
   $scope module mux $end
    $var wire 32 , DATA_WIDTH [31:0] $end
    $var wire 32 & ImmOp [31:0] $end
    $var wire 32 - OFFSET [31:0] $end
    $var wire 32 ) PC [31:0] $end
    $var wire  1 % PCsrc $end
    $var wire 32 * branch_PC [31:0] $end
    $var wire 32 + inc_PC [31:0] $end
    $var wire 32 ( next_PC [31:0] $end
   $upscope $end
  $upscope $end
 $upscope $end
$enddefinitions $end


#0
0#
1$
0%
b00000000000000000000000000000000 &
b00000000000000000000000000000000 '
b00000000000000000000000000000100 (
b00000000000000000000000000000000 )
b00000000000000000000000000000100 *
b00000000000000000000000000000000 +
b00000000000000000000000000100000 ,
b00000000000000000000000000000100 -
#1
1#
#2
0#
#3
1#
#4
0#
0$
#5
1#
b00000000000000000000000000000100 '
b00000000000000000000000000001000 (
b00000000000000000000000000000100 )
b00000000000000000000000000001000 *
b00000000000000000000000000000100 +
#6
0#
#7
1#
b00000000000000000000000000001000 '
b00000000000000000000000000001100 (
b00000000000000000000000000001000 )
b00000000000000000000000000001100 *
b00000000000000000000000000001000 +
#8
0#
#9
1#
b00000000000000000000000000001100 '
b00000000000000000000000000010000 (
b00000000000000000000000000001100 )
b00000000000000000000000000010000 *
b00000000000000000000000000001100 +
#10
0#
1%
b00000000000000000000000000010000 &
b00000000000000000000000000011100 (
b00000000000000000000000000011100 +
#11
1#
b00000000000000000000000000010000 '
b00000000000000000000000000100000 (
b00000000000000000000000000010000 )
b00000000000000000000000000010100 *
b00000000000000000000000000100000 +
#12
0#
0%
b00000000000000000000000000000000 &
b00000000000000000000000000010100 (
b00000000000000000000000000010000 +
#13
1#
b00000000000000000000000000100000 '
b00000000000000000000000000100100 (
b00000000000000000000000000100000 )
b00000000000000000000000000100100 *
b00000000000000000000000000100000 +
#14
0#
#15
1#
b00000000000000000000000000100100 '
b00000000000000000000000000101000 (
b00000000000000000000000000100100 )
b00000000000000000000000000101000 *
b00000000000000000000000000100100 +
#16
0#
#17
1#
b00000000000000000000000000101000 '
b00000000000000000000000000101100 (
b00000000000000000000000000101000 )
b00000000000000000000000000101100 *
b00000000000000000000000000101000 +
#18
0#
1%
b00000000000000000000000000010000 &
b00000000000000000000000000111000 (
b00000000000000000000000000111000 +
#19
1#
b00000000000000000000000000101100 '
b00000000000000000000000000111100 (
b00000000000000000000000000101100 )
b00000000000000000000000000110000 *
b00000000000000000000000000111100 +
#20
0#
0%
b00000000000000000000000000000000 &
b00000000000000000000000000110000 (
b00000000000000000000000000101100 +
#21
1#
b00000000000000000000000000111100 '
b00000000000000000000000001000000 (
b00000000000000000000000000111100 )
b00000000000000000000000001000000 *
b00000000000000000000000000111100 +
#22
0#
#23
1#
b00000000000000000000000001000000 '
b00000000000000000000000001000100 (
b00000000000000000000000001000000 )
b00000000000000000000000001000100 *
b00000000000000000000000001000000 +
#24
0#
#25
1#
b00000000000000000000000001000100 '
b00000000000000000000000001001000 (
b00000000000000000000000001000100 )
b00000000000000000000000001001000 *
b00000000000000000000000001000100 +
#26
0#
1%
b00000000000000000000000000010000 &
b00000000000000000000000001010100 (
b00000000000000000000000001010100 +
#27
1#
b00000000000000000000000001001000 '
b00000000000000000000000001011000 (
b00000000000000000000000001001000 )
b00000000000000000000000001001100 *
b00000000000000000000000001011000 +
#28
0#
0%
b00000000000000000000000000000000 &
b00000000000000000000000001001100 (
b00000000000000000000000001001000 +
#29
1#
b00000000000000000000000001011000 '
b00000000000000000000000001011100 (
b00000000000000000000000001011000 )
b00000000000000000000000001011100 *
b00000000000000000000000001011000 +
#30
0#
#31
1#
b00000000000000000000000001011100 '
b00000000000000000000000001100000 (
b00000000000000000000000001011100 )
b00000000000000000000000001100000 *
b00000000000000000000000001011100 +
#32
0#
#33
1#
b00000000000000000000000001100000 '
b00000000000000000000000001100100 (
b00000000000000000000000001100000 )
b00000000000000000000000001100100 *
b00000000000000000000000001100000 +
#34
0#
1%
b00000000000000000000000000010000 &
b00000000000000000000000001110000 (
b00000000000000000000000001110000 +
#35
1#
b00000000000000000000000001100100 '
b00000000000000000000000001110100 (
b00000000000000000000000001100100 )
b00000000000000000000000001101000 *
b00000000000000000000000001110100 +
#36
0#
0%
b00000000000000000000000000000000 &
b00000000000000000000000001101000 (
b00000000000000000000000001100100 +
#37
1#
b00000000000000000000000001110100 '
b00000000000000000000000001111000 (
b00000000000000000000000001110100 )
b00000000000000000000000001111000 *
b00000000000000000000000001110100 +
#38
0#
#39
1#
b00000000000000000000000001111000 '
b00000000000000000000000001111100 (
b00000000000000000000000001111000 )
b00000000000000000000000001111100 *
b00000000000000000000000001111000 +
