components/Control_and_InstMem/sign_extend.sv

//module to sign extend the immediate value of the instruction
module sign_extend (
    input  logic [31:0] instruction,  
    input  logic [6:0]  opcode,       
    output logic [31:0] imm_ext       
);

    always_comb begin
        imm_ext = 32'b0; 

        case(opcode)
            7'b0010011: begin // I-type (addi)
                imm_ext = {{20{instruction[31]}}, instruction[31:20]};
            end
            
            7'b1100011: begin // B-type (bne)
                imm_ext = {{19{instruction[31]}}, instruction[31],
                          instruction[7], instruction[30:25],
                          instruction[11:8], 1'b0};
            end
            
            default: begin
                imm_ext = 32'b0;
            end
        endcase
    end
endmodule

components/Control_and_InstMem/control_unit.sv
// module to sign extend the immediate value of the instruction
module control_unit (
    input  logic [6:0] opcode,     
    input  logic [2:0] funct3,     
    output logic       reg_write,  
    output logic       alu_src,     
    output logic       branch,      
    output logic [2:0] alu_op 
);


    always_comb begin

        reg_write = 1'b0;
        alu_src   = 1'b0;
        branch    = 1'b0;
        alu_op    = 3'b000;

        case(opcode)
            7'b0010011: begin // I-type (addi)
                reg_write = 1'b1;
                alu_src   = 1'b1;
                branch    = 1'b0;
                alu_op    = 3'b000;
            end
            
            7'b1100011: begin // B-type (bne)
                reg_write = 1'b0;
                alu_src   = 1'b0;
                branch    = 1'b1;
                alu_op    = 3'b001;
            end

            default: begin
                reg_write = 1'b0;
                alu_src   = 1'b0;
                branch    = 1'b0;
                alu_op    = 3'b000;
            end
        endcase
    end
endmodule

components/Control_and_InstMem/instr_mem.sv
// module to sign extend the immediate value of the instruction
module instr_mem #(
    parameter ADDR_WIDTH = 8,
    parameter INSTR_WIDTH = 32
)(
    input  logic [ADDR_WIDTH-1:0] pc,
    output logic [INSTR_WIDTH-1:0] instr
);

    logic [INSTR_WIDTH-1:0] rom [0:(2**ADDR_WIDTH)-1];
    
    assign instr = rom[pc];
    
    initial begin
        $readmemh("program.mem", rom);
    end
endmodule

RISC-V-Flavio/Control_and_InstMem/top.sv
module top (
    input  logic        clk,         // 时钟信号
    input  logic        rst,         // 复位信号
    input  logic [7:0]  pc,          // 程序计数器
    output logic [31:0] instruction, // 指令
    output logic        reg_write,   // 寄存器写使能
    output logic        alu_src,     // ALU输入选择
    output logic        branch,      // 分支控制
    output logic [2:0]  alu_op,      // ALU操作码
    output logic [31:0] imm_ext      // 扩展后的立即数
);

    // 内部信号
    logic [6:0] opcode;
    logic [2:0] funct3;
    
    // 直接从指令中提取字段，不需要额外的寄存器
    assign opcode = instruction[6:0];
    assign funct3 = instruction[14:12];
    
    // 实例化指令存储器
    instr_mem #(
        .ADDR_WIDTH(8),
        .INSTR_WIDTH(32)
    ) imem (
        .pc(pc),
        .instr(instruction)
    );
    
    // 实例化控制单元
    control_unit ctrl_unit (
        .opcode(opcode),
        .funct3(funct3),
        .reg_write(reg_write),
        .alu_src(alu_src),
        .branch(branch),
        .alu_op(alu_op)
    );
    
    // 实例化符号扩展单元
    sign_extend sign_ext (
        .instruction(instruction),  // 直接使用instruction
        .opcode(opcode),
        .imm_ext(imm_ext)
    );

    // 使用时钟和复位信号的同步逻辑
    always_ff @(posedge clk or posedge rst) begin
        if (rst) begin
            // 在复位时可以添加一些初始化逻辑
        end
    end

endmodule

components/Control_and_InstMem/waveform.vcd
$version Generated by VerilatedVcd $end
$timescale 1ps $end
 $scope module TOP $end
  $var wire 1 # clk $end
  $var wire 1 $ rst $end
  $var wire 8 % pc [7:0] $end
  $var wire 32 & instruction [31:0] $end
  $var wire 1 ' reg_write $end
  $var wire 1 ( alu_src $end
  $var wire 1 ) branch $end
  $var wire 3 * alu_op [2:0] $end
  $var wire 32 + imm_ext [31:0] $end
  $scope module top $end
   $var wire 1 # clk $end
   $var wire 1 $ rst $end
   $var wire 8 % pc [7:0] $end
   $var wire 32 & instruction [31:0] $end
   $var wire 1 ' reg_write $end
   $var wire 1 ( alu_src $end
   $var wire 1 ) branch $end
   $var wire 3 * alu_op [2:0] $end
   $var wire 32 + imm_ext [31:0] $end
   $var wire 7 , opcode [6:0] $end
   $var wire 3 - funct3 [2:0] $end
   $scope module ctrl_unit $end
    $var wire 7 , opcode [6:0] $end
    $var wire 3 - funct3 [2:0] $end
    $var wire 1 ' reg_write $end
    $var wire 1 ( alu_src $end
    $var wire 1 ) branch $end
    $var wire 3 * alu_op [2:0] $end
   $upscope $end
   $scope module imem $end
    $var wire 32 . ADDR_WIDTH [31:0] $end
    $var wire 32 / INSTR_WIDTH [31:0] $end
    $var wire 8 % pc [7:0] $end
    $var wire 32 & instr [31:0] $end
   $upscope $end
   $scope module sign_ext $end
    $var wire 32 & instruction [31:0] $end
    $var wire 7 , opcode [6:0] $end
    $var wire 32 + imm_ext [31:0] $end
   $upscope $end
  $upscope $end
 $upscope $end
$enddefinitions $end


#0
0#
0$
b00000000 %
b00000000000000000000001010010011 &
1'
1(
0)
b000 *
b00000000000000000000000000000000 +
b0010011 ,
b000 -
b00000000000000000000000000001000 .
b00000000000000000000000000100000 /
#1
b00000001 %
b00000000000100101000001100010011 &
b00000000000000000000000000000001 +
#2
b00000010 %
b11111110011000101001100011100011 &
0'
0(
1)
b001 *
b11111111111111111111111111110000 +
b1100011 ,
b001 -
#3
b00000000 %
b00000000000000000000001010010011 &
1'
1(
0)
b000 *
b00000000000000000000000000000000 +
b0010011 ,
b000 -
#4
b00000001 %
b00000000000100101000001100010011 &
b00000000000000000000000000000001 +
#5
b00000010 %
b11111110011000101001100011100011 &
0'
0(
1)
b001 *
b11111111111111111111111111110000 +
b1100011 ,
b001 -
#6
b00000000 %
b00000000000000000000001010010011 &
1'
1(
0)
b000 *
b00000000000000000000000000000000 +
b0010011 ,
b000 -
#7
b00000001 %
b00000000000100101000001100010011 &
b00000000000000000000000000000001 +
#8
b00000010 %
b11111110011000101001100011100011 &
0'
0(
1)
b001 *
b11111111111111111111111111110000 +
b1100011 ,
b001 -
#9
b00000000 %
b00000000000000000000001010010011 &
1'
1(
0)
b000 *
b00000000000000000000000000000000 +
b0010011 ,
b000 -
