main/rtl/mux2.sv
module mux2 #(
    parameter ADDR_WIDTH = 16
) (
    input   logic [ADDR_WIDTH-1:0]  branch_PC,
    input   logic [ADDR_WIDTH-1:0]  inc_PC,
    input   logic                   PCsrc,
    output  logic [ADDR_WIDTH-1:0]  next_PC
);


    assign next_PC = PCsrc ? branch_PC : inc_PC;

endmodule

main/PCReg.sv
module PCReg #(
    DATA_WIDTH = 32
) (
    input   logic [DATA_WIDTH-1:0]  next_PC,
    input   logic                   clk,
    input   logic                   rst,
    output  logic [DATA_WIDTH-1:0]  PC
);

    always_ff @ (posedge clk, posedge rst)
        if (rst)
            PC <= 32'b0;
        else
            PC <= next_PC;

endmodule

main/rtl/ALU.sv
module ALU #(
    parameter DATA_WIDTH = 32
) (
    input   logic [DATA_WIDTH-1:0]  ALUop1,
    input   logic [DATA_WIDTH-1:0]  ALUop2,
    input   logic [2:0]             ALUctrl,
    output  logic [DATA_WIDTH-1:0]  ALUout,
    output  logic                   EQ
);

    logic [DATA_WIDTH-1:0] addi;
    logic [DATA_WIDTH-1:0] sub;
    logic [DATA_WIDTH-1:0] andA;
    logic [DATA_WIDTH-1:0] orA; 
    logic [DATA_WIDTH-1:0] bne;
    logic                  match;
    
always_comb begin
    match = 0;
    addi = ALUop1 + ALUop2;
    sub = ALUop1 - ALUop2;
    andA = ALUop1 & ALUop2;
    orA = ALUop1 | ALUop2;
    if (sub == 0 && ALUctrl == 4) 
        match = 1'b1;
    case (ALUctrl)
        0: ALUout = addi;
        1: ALUout = sub;
        2: ALUout = andA;
        3: ALUout = orA;
        4: ALUout = 0;
        default: ALUout = 0;
    endcase

    EQ = match;
end



endmodule

main/rtl/mux.sv
module mux #(
    parameter DATA_WIDTH = 32
) (
    input   logic [DATA_WIDTH-1:0]  ImmOp,
    input   logic [DATA_WIDTH-1:0]  regOp2,
    input   logic                   ALUsrc,
    output  logic [DATA_WIDTH-1:0]  ALUop2
);


    assign ALUop2 = ALUsrc ? ImmOp : regOp2;

endmodule

main/RegFile.sv
module RegFile #(
    parameter DATA_WIDTH = 32,
    parameter REG_DATA_WIDTH = 5
) (
    input   logic [REG_DATA_WIDTH-1:0]  rs1,
    input   logic [REG_DATA_WIDTH-1:0]  rs2,
    input   logic [REG_DATA_WIDTH-1:0]  rd,
    input   logic [DATA_WIDTH-1:0]      ALUout,
    input   logic                       clk,
    input   logic                       RegWrite,
    output  logic [DATA_WIDTH-1:0]      a0,
    output  logic [DATA_WIDTH-1:0]      ALUop1,
    output  logic [DATA_WIDTH-1:0]      regOp2
);

    logic [DATA_WIDTH-1:0] rom_array [2**REG_DATA_WIDTH-1:0];

    // Initialize rom_array in simulation only
    initial begin
        $display("Loading rom.1");
        $readmemh("reg.mem", rom_array);
    end

    // Write and Read Logic
    always_ff @(posedge clk) begin
        if (RegWrite) begin
            rom_array[rd] <= ALUout;  // Write to register
        end 
        else begin
            ALUop1 <= rom_array[rs1]; // Read first operand
            regOp2 <= rom_array[rs2]; // Read second operand
        end
    end

    // Continuous assignment for a0
    assign a0 = rom_array[rd];

endmodule

main/rtl/control_unit.sv
module control_unit (
    input  logic [6:0] opcode,
    input  logic [2:0] funct3,
    input  logic       eq,
    output logic       reg_write,
    output logic       alu_src,
    output logic       branch,
    output logic [2:0] alu_op,
    output logic       immSrc,
    output logic       PCsrc
);

    always_comb begin
        reg_write = 1'b0;
        alu_src   = 1'b0;
        branch    = 1'b0;
        PCsrc     = 1'b0;
        alu_op    = 3'b000;
        immSrc    = 1'b0;

        case (opcode)
            7'b0010011: begin // I-type, addi instruction
                reg_write = 1'b1;
                alu_src   = 1'b1;
                branch    = 1'b0;
                alu_op    = 3'b000;
                immSrc    = 1'b0;
            end
            
            7'b1100011: begin // B-type, bne instruction
                reg_write = 1'b0;
                alu_src   = 1'b0;
                branch    = 1'b1;
                alu_op    = 3'b001;
                immSrc    = 1'b1;

                case (funct3)
                    3'b001: PCsrc = ~eq;
                    3'b000: PCsrc = eq;
                    default: PCsrc = 1'b0;
                endcase
            end

            default: begin
                reg_write = 1'b0;
                alu_src   = 1'b0;
                branch    = 1'b0;
                PCsrc     = 1'b0;
                alu_op    = 3'b000;
                immSrc    = 1'b0;
            end
        endcase
    end

endmodule

main/rtl/sign_extend.sv
module sign_extend (
    input  logic [31:0] instruction,  
    input  logic        immSrc,       
    output logic [31:0] imm_ext       
);

    always_comb begin
        if (immSrc)
            imm_ext = {{20{instruction[31]}}, instruction[7], instruction[30:25], instruction[11:8], 1'b0};
        else
            imm_ext = {{20{instruction[31]}}, instruction[31:20]};
    end
endmodule

main/rtl/instr_mem.sv
// module to sign extend the immediate value of the instruction
module instr_mem #(
    parameter ADDR_WIDTH = 32,
    parameter INSTR_WIDTH = 32
)(
    input  logic [ADDR_WIDTH-1:0] pc,
    output logic [INSTR_WIDTH-1:0] instr
);

    logic [INSTR_WIDTH-1:0] rom [(2**ADDR_WIDTH)-1:0];
    
    assign instr = rom[pc];
    
    initial begin
        $readmemh("/home/kali/Lab4/main/rtl/program.hex", rom);
    end
endmodule

main/rtl/top.sv
module top #(
    parameter DATA_WIDTH = 32,
    parameter INSTR_WIDTH = 32,
    parameter ADDR_WIDTH = 16,
    parameter REG_DATA_WIDTH = 5,
    parameter OFFSET = 1
) (
    input   logic                   clk,
    input   logic                   rst,
    output  logic [DATA_WIDTH-1:0]  a0
);

    logic [ADDR_WIDTH-1:0]  pc;
    logic [INSTR_WIDTH-1:0] instr;
    logic [INSTR_WIDTH-1:0] immOp;
    logic                   regWrite;
    logic [2:0]             aluCtrl;
    logic                   aluSrc;
    logic                   immSrc;
    logic                   pcSrc;
    logic [DATA_WIDTH-1:0]  aluOp1;
    logic [DATA_WIDTH-1:0]  aluOp2;
    logic [DATA_WIDTH-1:0]  regOp2;
    logic [DATA_WIDTH-1:0]  aluOut;
    logic                   eq;
    logic [ADDR_WIDTH-1:0]  nextPC;
    logic [ADDR_WIDTH-1:0]  branchPC;
    logic [ADDR_WIDTH-1:0]  incPC;
    
    instr_mem #(
        .ADDR_WIDTH(ADDR_WIDTH),
        .INSTR_WIDTH(INSTR_WIDTH)
    ) imem (
        .pc (pc),
        .instr (instr)
    );

    sign_extend sign_ext (
        .instruction(instr),
        .immSrc(immSrc),
        .imm_ext(immOp)
    );

    control_unit ctrl_unit (
        .opcode (instr[6:0]),
        .funct3 (instr[14:12]),
        .reg_write (regWrite),
        .eq (eq),
        .alu_src (aluSrc),
        .branch (pcSrc),
        .alu_op (aluCtrl),
        .immSrc (immSrc),
        .PCsrc(pcSrc)
    );

    RegFile #(
        .DATA_WIDTH(DATA_WIDTH),
        .REG_DATA_WIDTH(REG_DATA_WIDTH)
    ) RegFile (
        .clk (clk),
        .rs1 (instr[19:15]),
        .rs2 (instr[24:20]),
        .rd (instr[11:7]),
        .RegWrite (regWrite),
        .ALUout (aluOut),
        .a0 (a0),
        .ALUop1 (aluOp1),
        .regOp2 (regOp2)
    );

    mux regFileMux (
        .ImmOp (immOp),
        .regOp2 (regOp2),
        .ALUsrc (aluSrc),
        .ALUop2 (aluOp2)
    );

    ALU regFileALU (
        .ALUop1 (aluOp1),
        .ALUop2 (aluOp2),
        .ALUctrl (aluCtrl),
        .ALUout (aluOut),
        .EQ (eq)
    );

    PCReg PCReg (
        .clk (clk),
        .rst (rst),
        .PC (pc),
        .next_PC (nextPC)
    );

    mux2 pcMux (
        .inc_PC (incPC),
        .branch_PC (branchPC),
        .PCsrc (pcSrc),
        .next_PC (nextPC)
    );

    always_comb begin
        incPC = pc + OFFSET;
        branchPC = pc + immOp[15:0];
    end

endmodule

main/tb/waveform.vcd
$version Generated by VerilatedVcd $end
$date Thu Nov 28 05:08:16 2024 $end
$timescale 1ps $end

 $scope module TOP $end
  $var wire 32 _ a0 [31:0] $end
  $var wire  1 ] clk $end
  $var wire  1 ^ rst $end
  $scope module top $end
   $var wire 32 a ADDR_WIDTH [31:0] $end
   $var wire 32 ` DATA_WIDTH [31:0] $end
   $var wire 32 ` INSTR_WIDTH [31:0] $end
   $var wire 32 c OFFSET [31:0] $end
   $var wire 32 b REG_DATA_WIDTH [31:0] $end
   $var wire 32 _ a0 [31:0] $end
   $var wire  3 ' aluCtrl [2:0] $end
   $var wire 32 + aluOp1 [31:0] $end
   $var wire 32 , aluOp2 [31:0] $end
   $var wire 32 . aluOut [31:0] $end
   $var wire  1 ( aluSrc $end
   $var wire 16 1 branchPC [15:0] $end
   $var wire  1 ] clk $end
   $var wire  1 / eq $end
   $var wire 32 % immOp [31:0] $end
   $var wire  1 ) immSrc $end
   $var wire 16 2 incPC [15:0] $end
   $var wire 32 $ instr [31:0] $end
   $var wire 16 0 nextPC [15:0] $end
   $var wire 16 # pc [15:0] $end
   $var wire  1 * pcSrc $end
   $var wire 32 - regOp2 [31:0] $end
   $var wire  1 & regWrite $end
   $var wire  1 ^ rst $end
   $scope module PCReg $end
    $var wire 32 a DATA_WIDTH [31:0] $end
    $var wire 16 # PC [15:0] $end
    $var wire  1 ] clk $end
    $var wire 16 0 next_PC [15:0] $end
    $var wire  1 ^ rst $end
   $upscope $end
   $scope module RegFile $end
    $var wire 32 + ALUop1 [31:0] $end
    $var wire 32 . ALUout [31:0] $end
    $var wire 32 ` DATA_WIDTH [31:0] $end
    $var wire 32 b REG_DATA_WIDTH [31:0] $end
    $var wire  1 & RegWrite $end
    $var wire 32 _ a0 [31:0] $end
    $var wire  1 ] clk $end
    $var wire  5 5 rd [4:0] $end
    $var wire 32 - regOp2 [31:0] $end
    $var wire 32 6 rom_array[0] [31:0] $end
    $var wire 32 @ rom_array[10] [31:0] $end
    $var wire 32 A rom_array[11] [31:0] $end
    $var wire 32 B rom_array[12] [31:0] $end
    $var wire 32 C rom_array[13] [31:0] $end
    $var wire 32 D rom_array[14] [31:0] $end
    $var wire 32 E rom_array[15] [31:0] $end
    $var wire 32 F rom_array[16] [31:0] $end
    $var wire 32 G rom_array[17] [31:0] $end
    $var wire 32 H rom_array[18] [31:0] $end
    $var wire 32 I rom_array[19] [31:0] $end
    $var wire 32 7 rom_array[1] [31:0] $end
    $var wire 32 J rom_array[20] [31:0] $end
    $var wire 32 K rom_array[21] [31:0] $end
    $var wire 32 L rom_array[22] [31:0] $end
    $var wire 32 M rom_array[23] [31:0] $end
    $var wire 32 N rom_array[24] [31:0] $end
    $var wire 32 O rom_array[25] [31:0] $end
    $var wire 32 P rom_array[26] [31:0] $end
    $var wire 32 Q rom_array[27] [31:0] $end
    $var wire 32 R rom_array[28] [31:0] $end
    $var wire 32 S rom_array[29] [31:0] $end
    $var wire 32 8 rom_array[2] [31:0] $end
    $var wire 32 T rom_array[30] [31:0] $end
    $var wire 32 U rom_array[31] [31:0] $end
    $var wire 32 9 rom_array[3] [31:0] $end
    $var wire 32 : rom_array[4] [31:0] $end
    $var wire 32 ; rom_array[5] [31:0] $end
    $var wire 32 < rom_array[6] [31:0] $end
    $var wire 32 = rom_array[7] [31:0] $end
    $var wire 32 > rom_array[8] [31:0] $end
    $var wire 32 ? rom_array[9] [31:0] $end
    $var wire  5 3 rs1 [4:0] $end
    $var wire  5 4 rs2 [4:0] $end
   $upscope $end
   $scope module ctrl_unit $end
    $var wire  1 * PCsrc $end
    $var wire  3 ' alu_op [2:0] $end
    $var wire  1 ( alu_src $end
    $var wire  1 * branch $end
    $var wire  1 / eq $end
    $var wire  3 W funct3 [2:0] $end
    $var wire  1 ) immSrc $end
    $var wire  7 V opcode [6:0] $end
    $var wire  1 & reg_write $end
   $upscope $end
   $scope module imem $end
    $var wire 32 a ADDR_WIDTH [31:0] $end
    $var wire 32 ` INSTR_WIDTH [31:0] $end
    $var wire 32 $ instr [31:0] $end
    $var wire 16 # pc [15:0] $end
   $upscope $end
   $scope module pcMux $end
    $var wire 32 a ADDR_WIDTH [31:0] $end
    $var wire  1 * PCsrc $end
    $var wire 16 1 branch_PC [15:0] $end
    $var wire 16 2 inc_PC [15:0] $end
    $var wire 16 0 next_PC [15:0] $end
   $upscope $end
   $scope module regFileALU $end
    $var wire  3 ' ALUctrl [2:0] $end
    $var wire 32 + ALUop1 [31:0] $end
    $var wire 32 , ALUop2 [31:0] $end
    $var wire 32 . ALUout [31:0] $end
    $var wire 32 ` DATA_WIDTH [31:0] $end
    $var wire  1 / EQ $end
    $var wire 32 X addi [31:0] $end
    $var wire 32 Z andA [31:0] $end
    $var wire  1 \ match $end
    $var wire 32 [ orA [31:0] $end
    $var wire 32 Y sub [31:0] $end
   $upscope $end
   $scope module regFileMux $end
    $var wire 32 , ALUop2 [31:0] $end
    $var wire  1 ( ALUsrc $end
    $var wire 32 ` DATA_WIDTH [31:0] $end
    $var wire 32 % ImmOp [31:0] $end
    $var wire 32 - regOp2 [31:0] $end
   $upscope $end
   $scope module sign_ext $end
    $var wire  1 ) immSrc $end
    $var wire 32 % imm_ext [31:0] $end
    $var wire 32 $ instruction [31:0] $end
   $upscope $end
  $upscope $end
 $upscope $end
$enddefinitions $end


#0
b0000000000000000 #
b00001111111100000000001100010011 $
b00000000000000000000000011111111 %
1&
b000 '
1(
0)
0*
b00000000000000000000000000000000 +
b00000000000000000000000011111111 ,
b00000000000000000000000000000000 -
b00000000000000000000000011111111 .
0/
b0000000000000001 0
b0000000011111111 1
b0000000000000001 2
b00000 3
b11111 4
b00110 5
b00000000000000000000000000000000 6
b00000000000000000000000000000001 7
b00000000000000000000000000000010 8
b00000000000000000000000000000011 9
b00000000000000000000000000000100 :
b00000000000000000000000000000101 ;
b00000000000000000000000000000110 <
b00000000000000000000000000000111 =
b00000000000000000000000000001000 >
b00000000000000000000000000001001 ?
b00000000000000000000000000010000 @
b00000000000000000000000000010001 A
b00000000000000000000000000010010 B
b00000000000000000000000000010011 C
b00000000000000000000000000010100 D
b00000000000000000000000000010101 E
b00000000000000000000000000010110 F
b00000000000000000000000000010111 G
b00000000000000000000000000011000 H
b00000000000000000000000000011001 I
b00000000000000000000000000100000 J
b00000000000000000000000000100001 K
b00000000000000000000000000100010 L
b00000000000000000000000000100011 M
b00000000000000000000000000100100 N
b00000000000000000000000000100101 O
b00000000000000000000000000100110 P
b00000000000000000000000000100111 Q
b00000000000000000000000000101000 R
b00000000000000000000000000101001 S
b00000000000000000000000000110000 T
b00000000000000000000000000110001 U
b0010011 V
b000 W
b00000000000000000000000011111111 X
b11111111111111111111111100000001 Y
b00000000000000000000000000000000 Z
b00000000000000000000000011111111 [
0\
1]
0^
b00000000000000000000000000000110 _
b00000000000000000000000000100000 `
b00000000000000000000000000010000 a
b00000000000000000000000000000101 b
b00000000000000000000000000000001 c
#1
0]
#2
b0000000000000001 #
b00000000000000000000010100010011 $
b00000000000000000000000000000000 %
b00000000000000000000000000000000 ,
b00000000000000000000000000000000 .
b0000000000000010 0
b0000000000000001 1
b0000000000000010 2
b00000 4
b01010 5
b00000000000000000000000011111111 <
b00000000000000000000000000000000 X
b00000000000000000000000000000000 Y
b00000000000000000000000000000000 [
1]
b00000000000000000000000000010000 _
#3
0]
#4
b0000000000000010 #
b00000000000000000000010110010011 $
b0000000000000011 0
b0000000000000010 1
b0000000000000011 2
b01011 5
b00000000000000000000000000000000 @
1]
b00000000000000000000000000010001 _
#5
0]
#6
b0000000000000011 #
b00000000000001011000010100010011 $
b0000000000000100 0
b0000000000000011 1
b0000000000000100 2
b01011 3
b01010 5
b00000000000000000000000000000000 A
1]
b00000000000000000000000000000000 _
#7
0]
#8
b0000000000000100 #
b00000000000101011000010110010011 $
b00000000000000000000000000000001 %
b00000000000000000000000000000001 ,
b00000000000000000000000000000001 .
b0000000000000101 0
b0000000000000101 1
b0000000000000101 2
b00001 4
b01011 5
b00000000000000000000000000000001 X
b11111111111111111111111111111111 Y
b00000000000000000000000000000001 [
1]
#9
0]
#10
b0000000000000101 #
b11111110011001011001110011100011 $
b11111111111111111111111111111000 %
0&
b001 '
0(
1)
1*
b00000000000000000000000000000000 ,
b00000000000000000000000000000000 .
b1111111111111101 0
b1111111111111101 1
b0000000000000110 2
b00110 4
b11001 5
b00000000000000000000000000000001 A
b1100011 V
b001 W
b00000000000000000000000000000000 X
b00000000000000000000000000000000 Y
b00000000000000000000000000000000 [
1]
b00000000000000000000000000100101 _
#11
0]
#12
b1111111111111101 #
b00000000000000000000000000000000 $
b00000000000000000000000000000000 %
b000 '
0)
0*
b00000000000000000000000000000001 +
b00000000000000000000000011111111 ,
b00000000000000000000000011111111 -
b00000000000000000000000100000000 .
b1111111111111110 0
b1111111111111110 2
b00000 3
b00000 4
b00000 5
b0000000 V
b000 W
b00000000000000000000000100000000 X
b11111111111111111111111100000010 Y
b00000000000000000000000000000001 Z
b00000000000000000000000011111111 [
1]
b00000000000000000000000000000000 _
#13
0]
#14
b1111111111111110 #
b00000000000000000000000000000000 +
b00000000000000000000000000000000 ,
b00000000000000000000000000000000 -
b00000000000000000000000000000000 .
b1111111111111111 0
b1111111111111110 1
b1111111111111111 2
b00000000000000000000000000000000 X
b00000000000000000000000000000000 Y
b00000000000000000000000000000000 Z
b00000000000000000000000000000000 [
1]
#15
0]
#16
b1111111111111111 #
b0000000000000000 0
b1111111111111111 1
b0000000000000000 2
1]
#17
0]
#18
b0000000000000000 #
b00001111111100000000001100010011 $
b00000000000000000000000011111111 %
1&
1(
b00000000000000000000000011111111 ,
b00000000000000000000000011111111 .
b0000000000000001 0
b0000000011111111 1
b0000000000000001 2
b11111 4
b00110 5
b0010011 V
b00000000000000000000000011111111 X
b11111111111111111111111100000001 Y
b00000000000000000000000011111111 [
1]
b00000000000000000000000011111111 _
#19
0]
#20
b0000000000000001 #
b00000000000000000000010100010011 $
b00000000000000000000000000000000 %
b00000000000000000000000000000000 ,
b00000000000000000000000000000000 .
b0000000000000010 0
b0000000000000001 1
b0000000000000010 2
b00000 4
b01010 5
b00000000000000000000000000000000 X
b00000000000000000000000000000000 Y
b00000000000000000000000000000000 [
1]
b00000000000000000000000000000000 _
#21
0]
#22
b0000000000000010 #
b00000000000000000000010110010011 $
b0000000000000011 0
b0000000000000010 1
b0000000000000011 2
b01011 5
1]
b00000000000000000000000000000001 _
#23
0]
#24
b0000000000000011 #
b00000000000001011000010100010011 $
b0000000000000100 0
b0000000000000011 1
b0000000000000100 2
b01011 3
b01010 5
b00000000000000000000000000000000 A
1]
b00000000000000000000000000000000 _
#25
0]
#26
b0000000000000100 #
b00000000000101011000010110010011 $
b00000000000000000000000000000001 %
b00000000000000000000000000000001 ,
b00000000000000000000000000000001 .
b0000000000000101 0
b0000000000000101 1
b0000000000000101 2
b00001 4
b01011 5
b00000000000000000000000000000001 X
b11111111111111111111111111111111 Y
b00000000000000000000000000000001 [
1]
#27
0]
#28
b0000000000000101 #
b11111110011001011001110011100011 $
b11111111111111111111111111111000 %
0&
b001 '
0(
1)
1*
b00000000000000000000000000000000 ,
b00000000000000000000000000000000 .
b1111111111111101 0
b1111111111111101 1
b0000000000000110 2
b00110 4
b11001 5
b00000000000000000000000000000001 A
b1100011 V
b001 W
b00000000000000000000000000000000 X
b00000000000000000000000000000000 Y
b00000000000000000000000000000000 [
1]
b00000000000000000000000000100101 _
#29
0]
#30
b1111111111111101 #
b00000000000000000000000000000000 $
b00000000000000000000000000000000 %
b000 '
0)
0*
b00000000000000000000000000000001 +
b00000000000000000000000011111111 ,
b00000000000000000000000011111111 -
b00000000000000000000000100000000 .
b1111111111111110 0
b1111111111111110 2
b00000 3
b00000 4
b00000 5
b0000000 V
b000 W
b00000000000000000000000100000000 X
b11111111111111111111111100000010 Y
b00000000000000000000000000000001 Z
b00000000000000000000000011111111 [
1]
b00000000000000000000000000000000 _
#31
0]
#32
b1111111111111110 #
b00000000000000000000000000000000 +
b00000000000000000000000000000000 ,
b00000000000000000000000000000000 -
b00000000000000000000000000000000 .
b1111111111111111 0
b1111111111111110 1
b1111111111111111 2
b00000000000000000000000000000000 X
b00000000000000000000000000000000 Y
b00000000000000000000000000000000 Z
b00000000000000000000000000000000 [
1]
#33
0]
#34
b1111111111111111 #
b0000000000000000 0
b1111111111111111 1
b0000000000000000 2
1]
#35
0]
#36
b0000000000000000 #
b00001111111100000000001100010011 $
b00000000000000000000000011111111 %
1&
1(
b00000000000000000000000011111111 ,
b00000000000000000000000011111111 .
b0000000000000001 0
b0000000011111111 1
b0000000000000001 2
b11111 4
b00110 5
b0010011 V
b00000000000000000000000011111111 X
b11111111111111111111111100000001 Y
b00000000000000000000000011111111 [
1]
b00000000000000000000000011111111 _
#37
0]
#38
b0000000000000001 #
b00000000000000000000010100010011 $
b00000000000000000000000000000000 %
b00000000000000000000000000000000 ,
b00000000000000000000000000000000 .
b0000000000000010 0
b0000000000000001 1
b0000000000000010 2
b00000 4
b01010 5
b00000000000000000000000000000000 X
b00000000000000000000000000000000 Y
b00000000000000000000000000000000 [
1]
b00000000000000000000000000000000 _
#39
0]
#40
b0000000000000010 #
b00000000000000000000010110010011 $
b0000000000000011 0
b0000000000000010 1
b0000000000000011 2
b01011 5
1]
b00000000000000000000000000000001 _
#41
0]
#42
b0000000000000011 #
b00000000000001011000010100010011 $
b0000000000000100 0
b0000000000000011 1
b0000000000000100 2
b01011 3
b01010 5
b00000000000000000000000000000000 A
1]
b00000000000000000000000000000000 _
#43
0]
#44
b0000000000000100 #
b00000000000101011000010110010011 $
b00000000000000000000000000000001 %
b00000000000000000000000000000001 ,
b00000000000000000000000000000001 .
b0000000000000101 0
b0000000000000101 1
b0000000000000101 2
b00001 4
b01011 5
b00000000000000000000000000000001 X
b11111111111111111111111111111111 Y
b00000000000000000000000000000001 [
1]
#45
0]
#46
b0000000000000101 #
b11111110011001011001110011100011 $
b11111111111111111111111111111000 %
0&
b001 '
0(
1)
1*
b00000000000000000000000000000000 ,
b00000000000000000000000000000000 .
b1111111111111101 0
b1111111111111101 1
b0000000000000110 2
b00110 4
b11001 5
b00000000000000000000000000000001 A
b1100011 V
b001 W
b00000000000000000000000000000000 X
b00000000000000000000000000000000 Y
b00000000000000000000000000000000 [
1]
b00000000000000000000000000100101 _
#47
0]
#48
b1111111111111101 #
b00000000000000000000000000000000 $
b00000000000000000000000000000000 %
b000 '
0)
0*
b00000000000000000000000000000001 +
b00000000000000000000000011111111 ,
b00000000000000000000000011111111 -
b00000000000000000000000100000000 .
b1111111111111110 0
b1111111111111110 2
b00000 3
b00000 4
b00000 5
b0000000 V
b000 W
b00000000000000000000000100000000 X
b11111111111111111111111100000010 Y
b00000000000000000000000000000001 Z
b00000000000000000000000011111111 [
1]
b00000000000000000000000000000000 _
#49
0]
#50
b1111111111111110 #
b00000000000000000000000000000000 +
b00000000000000000000000000000000 ,
b00000000000000000000000000000000 -
b00000000000000000000000000000000 .
b1111111111111111 0
b1111111111111110 1
b1111111111111111 2
b00000000000000000000000000000000 X
b00000000000000000000000000000000 Y
b00000000000000000000000000000000 Z
b00000000000000000000000000000000 [
1]
#51
0]
#52
b1111111111111111 #
b0000000000000000 0
b1111111111111111 1
b0000000000000000 2
1]
#53
0]
#54
b0000000000000000 #
b00001111111100000000001100010011 $
b00000000000000000000000011111111 %
1&
1(
b00000000000000000000000011111111 ,
b00000000000000000000000011111111 .
b0000000000000001 0
b0000000011111111 1
b0000000000000001 2
b11111 4
b00110 5
b0010011 V
b00000000000000000000000011111111 X
b11111111111111111111111100000001 Y
b00000000000000000000000011111111 [
1]
b00000000000000000000000011111111 _
#55
0]
#56
b0000000000000001 #
b00000000000000000000010100010011 $
b00000000000000000000000000000000 %
b00000000000000000000000000000000 ,
b00000000000000000000000000000000 .
b0000000000000010 0
b0000000000000001 1
b0000000000000010 2
b00000 4
b01010 5
b00000000000000000000000000000000 X
b00000000000000000000000000000000 Y
b00000000000000000000000000000000 [
1]
b00000000000000000000000000000000 _
#57
0]
#58
b0000000000000010 #
b00000000000000000000010110010011 $
b0000000000000011 0
b0000000000000010 1
b0000000000000011 2
b01011 5
1]
b00000000000000000000000000000001 _
#59
0]
#60
b0000000000000011 #
b00000000000001011000010100010011 $
b0000000000000100 0
b0000000000000011 1
b0000000000000100 2
b01011 3
b01010 5
b00000000000000000000000000000000 A
1]
b00000000000000000000000000000000 _
#61
0]
#62
b0000000000000100 #
b00000000000101011000010110010011 $
b00000000000000000000000000000001 %
b00000000000000000000000000000001 ,
b00000000000000000000000000000001 .
b0000000000000101 0
b0000000000000101 1
b0000000000000101 2
b00001 4
b01011 5
b00000000000000000000000000000001 X
b11111111111111111111111111111111 Y
b00000000000000000000000000000001 [
1]
#63
0]
#64
b0000000000000101 #
b11111110011001011001110011100011 $
b11111111111111111111111111111000 %
0&
b001 '
0(
1)
1*
b00000000000000000000000000000000 ,
b00000000000000000000000000000000 .
b1111111111111101 0
b1111111111111101 1
b0000000000000110 2
b00110 4
b11001 5
b00000000000000000000000000000001 A
b1100011 V
b001 W
b00000000000000000000000000000000 X
b00000000000000000000000000000000 Y
b00000000000000000000000000000000 [
1]
b00000000000000000000000000100101 _
#65
0]
#66
b1111111111111101 #
b00000000000000000000000000000000 $
b00000000000000000000000000000000 %
b000 '
0)
0*
b00000000000000000000000000000001 +
b00000000000000000000000011111111 ,
b00000000000000000000000011111111 -
b00000000000000000000000100000000 .
b1111111111111110 0
b1111111111111110 2
b00000 3
b00000 4
b00000 5
b0000000 V
b000 W
b00000000000000000000000100000000 X
b11111111111111111111111100000010 Y
b00000000000000000000000000000001 Z
b00000000000000000000000011111111 [
1]
b00000000000000000000000000000000 _
#67
0]
#68
b1111111111111110 #
b00000000000000000000000000000000 +
b00000000000000000000000000000000 ,
b00000000000000000000000000000000 -
b00000000000000000000000000000000 .
b1111111111111111 0
b1111111111111110 1
b1111111111111111 2
b00000000000000000000000000000000 X
b00000000000000000000000000000000 Y
b00000000000000000000000000000000 Z
b00000000000000000000000000000000 [
1]
#69
0]
#70
b1111111111111111 #
b0000000000000000 0
b1111111111111111 1
b0000000000000000 2
1]
#71
0]
#72
b0000000000000000 #
b00001111111100000000001100010011 $
b00000000000000000000000011111111 %
1&
1(
b00000000000000000000000011111111 ,
b00000000000000000000000011111111 .
b0000000000000001 0
b0000000011111111 1
b0000000000000001 2
b11111 4
b00110 5
b0010011 V
b00000000000000000000000011111111 X
b11111111111111111111111100000001 Y
b00000000000000000000000011111111 [
1]
b00000000000000000000000011111111 _
#73
0]
#74
b0000000000000001 #
b00000000000000000000010100010011 $
b00000000000000000000000000000000 %
b00000000000000000000000000000000 ,
b00000000000000000000000000000000 .
b0000000000000010 0
b0000000000000001 1
b0000000000000010 2
b00000 4
b01010 5
b00000000000000000000000000000000 X
b00000000000000000000000000000000 Y
b00000000000000000000000000000000 [
1]
b00000000000000000000000000000000 _
#75
0]
#76
b0000000000000010 #
b00000000000000000000010110010011 $
b0000000000000011 0
b0000000000000010 1
b0000000000000011 2
b01011 5
1]
b00000000000000000000000000000001 _
#77
0]
#78
b0000000000000011 #
b00000000000001011000010100010011 $
b0000000000000100 0
b0000000000000011 1
b0000000000000100 2
b01011 3
b01010 5
b00000000000000000000000000000000 A
1]
b00000000000000000000000000000000 _
#79
0]
#80
b0000000000000100 #
b00000000000101011000010110010011 $
b00000000000000000000000000000001 %
b00000000000000000000000000000001 ,
b00000000000000000000000000000001 .
b0000000000000101 0
b0000000000000101 1
b0000000000000101 2
b00001 4
b01011 5
b00000000000000000000000000000001 X
b11111111111111111111111111111111 Y
b00000000000000000000000000000001 [
1]
#81
0]
#82
b0000000000000101 #
b11111110011001011001110011100011 $
b11111111111111111111111111111000 %
0&
b001 '
0(
1)
1*
b00000000000000000000000000000000 ,
b00000000000000000000000000000000 .
b1111111111111101 0
b1111111111111101 1
b0000000000000110 2
b00110 4
b11001 5
b00000000000000000000000000000001 A
b1100011 V
b001 W
b00000000000000000000000000000000 X
b00000000000000000000000000000000 Y
b00000000000000000000000000000000 [
1]
b00000000000000000000000000100101 _
#83
0]
#84
b1111111111111101 #
b00000000000000000000000000000000 $
b00000000000000000000000000000000 %
b000 '
0)
0*
b00000000000000000000000000000001 +
b00000000000000000000000011111111 ,
b00000000000000000000000011111111 -
b00000000000000000000000100000000 .
b1111111111111110 0
b1111111111111110 2
b00000 3
b00000 4
b00000 5
b0000000 V
b000 W
b00000000000000000000000100000000 X
b11111111111111111111111100000010 Y
b00000000000000000000000000000001 Z
b00000000000000000000000011111111 [
1]
b00000000000000000000000000000000 _
#85
0]
#86
b1111111111111110 #
b00000000000000000000000000000000 +
b00000000000000000000000000000000 ,
b00000000000000000000000000000000 -
b00000000000000000000000000000000 .
b1111111111111111 0
b1111111111111110 1
b1111111111111111 2
b00000000000000000000000000000000 X
b00000000000000000000000000000000 Y
b00000000000000000000000000000000 Z
b00000000000000000000000000000000 [
1]
#87
0]
#88
b1111111111111111 #
b0000000000000000 0
b1111111111111111 1
b0000000000000000 2
1]
#89
0]
#90
b0000000000000000 #
b00001111111100000000001100010011 $
b00000000000000000000000011111111 %
1&
1(
b00000000000000000000000011111111 ,
b00000000000000000000000011111111 .
b0000000000000001 0
b0000000011111111 1
b0000000000000001 2
b11111 4
b00110 5
b0010011 V
b00000000000000000000000011111111 X
b11111111111111111111111100000001 Y
b00000000000000000000000011111111 [
1]
b00000000000000000000000011111111 _
#91
0]
#92
b0000000000000001 #
b00000000000000000000010100010011 $
b00000000000000000000000000000000 %
b00000000000000000000000000000000 ,
b00000000000000000000000000000000 .
b0000000000000010 0
b0000000000000001 1
b0000000000000010 2
b00000 4
b01010 5
b00000000000000000000000000000000 X
b00000000000000000000000000000000 Y
b00000000000000000000000000000000 [
1]
b00000000000000000000000000000000 _
#93
0]
#94
b0000000000000010 #
b00000000000000000000010110010011 $
b0000000000000011 0
b0000000000000010 1
b0000000000000011 2
b01011 5
1]
b00000000000000000000000000000001 _
#95
0]
