main/rtl/mux2.sv
module mux2 #(
    parameter ADDR_WIDTH = 12
) (
    input   logic [ADDR_WIDTH-1:0]  branch_PC,
    input   logic [ADDR_WIDTH-1:0]  inc_PC,
    input   logic                   PCsrc,
    output  logic [ADDR_WIDTH-1:0]  next_PC
);


    assign next_PC = PCsrc ? inc_PC : branch_PC;

endmodule

main/PCReg.sv
module PCReg #(
    DATA_WIDTH = 32
) (
    input   logic [DATA_WIDTH-1:0]  next_PC,
    input   logic                   clk,
    input   logic                   rst,
    output  logic [DATA_WIDTH-1:0]  PC
);

    always_ff @ (posedge clk, posedge rst)
        if (rst)
            PC <= 32'b0;
        else
            PC <= next_PC;

endmodule

main/rtl/ALU.sv
module ALU #(
    parameter DATA_WIDTH = 32
) (
    input   logic [DATA_WIDTH-1:0]  ALUop1,
    input   logic [DATA_WIDTH-1:0]  ALUop2,
    input   logic [2:0]             ALUctrl,
    output  logic [DATA_WIDTH-1:0]  ALUout,
    output  logic                   EQ
);

    logic [DATA_WIDTH-1:0] addi;
    logic [DATA_WIDTH-1:0] sub;
    logic [DATA_WIDTH-1:0] andA;
    logic [DATA_WIDTH-1:0] orA; 
    logic [DATA_WIDTH-1:0] bne;
    logic                  match;
    
always_comb begin
    match = 0;
    addi = ALUop1 + ALUop2;
    sub = ALUop1 - ALUop2;
    andA = ALUop1 & ALUop2;
    orA = ALUop1 | ALUop2;
    if (sub == 0 && ALUctrl == 4) 
        match = 1'b1;
    case (ALUctrl)
        0: ALUout = addi;
        1: ALUout = sub;
        2: ALUout = andA;
        3: ALUout = orA;
        4: ALUout = 0;
        default: ALUout = 0;
    endcase

    EQ = match;
end



endmodule

main/rtl/mux.sv
module mux #(
    parameter DATA_WIDTH = 32
) (
    input   logic [DATA_WIDTH-1:0]  ImmOp,
    input   logic [DATA_WIDTH-1:0]  regOp2,
    input   logic                   ALUsrc,
    output  logic [DATA_WIDTH-1:0]  ALUop2
);


    assign ALUop2 = ALUsrc ? ImmOp : regOp2;

endmodule

main/RegFile.sv
module RegFile #(
    parameter DATA_WIDTH = 32,
    parameter REG_DATA_WIDTH = 5
) (
    input   logic [REG_DATA_WIDTH-1:0]  rs1,
    input   logic [REG_DATA_WIDTH-1:0]  rs2,
    input   logic [REG_DATA_WIDTH-1:0]  rd,
    input   logic [DATA_WIDTH-1:0]      ALUout,
    input   logic                       clk,
    input   logic                       RegWrite,
    output  logic [DATA_WIDTH-1:0]      a0,
    output  logic [DATA_WIDTH-1:0]      ALUop1,
    output  logic [DATA_WIDTH-1:0]      regOp2
);

    logic [DATA_WIDTH-1:0] rom_array [2**REG_DATA_WIDTH-1:0];

    // Initialize rom_array in simulation only
    initial begin
        $display("Loading rom.1");
        $readmemh("reg.mem", rom_array);
    end

    // Write and Read Logic
    always_ff @(posedge clk) begin
        if (RegWrite) begin
            rom_array[rd] <= ALUout;  // Write to register
        end 
        else begin
            ALUop1 <= rom_array[rs1]; // Read first operand
            regOp2 <= rom_array[rs2]; // Read second operand
        end
    end

    // Continuous assignment for a0
    assign a0 = rom_array[rd];

endmodule

main/rtl/control_unit.sv
module control_unit (
    input  logic [6:0] opcode,
    input  logic [2:0] funct3,
    input  logic       eq,
    output logic       reg_write,
    output logic       alu_src,
    output logic       branch,
    output logic [2:0] alu_op,
    output logic       immSrc,
    output logic       PCsrc
);

    always_comb begin
        reg_write = 1'b0;
        alu_src   = 1'b0;
        branch    = 1'b0;
        PCsrc     = 1'b0;
        alu_op    = 3'b000;
        immSrc    = 1'b0;

        case (opcode)
            7'b0010011: begin // I-type, addi instruction
                reg_write = 1'b1;
                alu_src   = 1'b1;
                branch    = 1'b0;
                alu_op    = 3'b000;
                immSrc    = 1'b0;
            end
            
            7'b1100011: begin // B-type, bne instruction
                reg_write = 1'b0;
                alu_src   = 1'b0;
                branch    = 1'b1;
                alu_op    = 3'b001;
                immSrc    = 1'b1;

                case (funct3)
                    3'b001: PCsrc = ~eq;
                    3'b000: PCsrc = eq;
                    default: PCsrc = 1'b0;
                endcase
            end

            default: begin
                reg_write = 1'b0;
                alu_src   = 1'b0;
                branch    = 1'b0;
                PCsrc     = 1'b0;
                alu_op    = 3'b000;
                immSrc    = 1'b0;
            end
        endcase
    end

endmodule

main/rtl/sign_extend.sv
module sign_extend (
    input  logic [31:0] instruction,  
    input  logic        immSrc,       
    output logic [31:0] imm_ext       
);

    always_comb begin
        if (immSrc)
            imm_ext = {{20{instruction[31]}}, instruction[7], instruction[30:25], instruction[11:8], 1'b0};
        else
            imm_ext = {{20{instruction[31]}}, instruction[31:20]};
    end
endmodule

main/rtl/instr_mem.sv
// module to sign extend the immediate value of the instruction
module instr_mem #(
    parameter ADDR_WIDTH = 32,
    parameter INSTR_WIDTH = 32
)(
    input  logic [ADDR_WIDTH-1:0] pc,
    output logic [INSTR_WIDTH-1:0] instr
);

    logic [INSTR_WIDTH-1:0] rom [(2**ADDR_WIDTH)-1:0];
    
    assign instr = rom[pc];
    
    initial begin
        $readmemh("/home/kali/Lab4/main/rtl/program.hex", rom);
    end
endmodule

main/rtl/top.sv
module top #(
    parameter DATA_WIDTH = 32,
    parameter INSTR_WIDTH = 32,
    parameter ADDR_WIDTH = 16,
    parameter REG_DATA_WIDTH = 5,
    parameter OFFSET = 1
) (
    input   logic                   clk,
    input   logic                   rst,
    output  logic [DATA_WIDTH-1:0]  a0
);

    logic [ADDR_WIDTH-1:0]  pc;
    logic [INSTR_WIDTH-1:0] instr;
    logic [INSTR_WIDTH-1:0] immOp;
    logic                   regWrite;
    logic [2:0]             aluCtrl;
    logic                   aluSrc;
    logic                   immSrc;
    logic                   pcSrc;
    logic [DATA_WIDTH-1:0]  aluOp1;
    logic [DATA_WIDTH-1:0]  aluOp2;
    logic [DATA_WIDTH-1:0]  regOp2;
    logic [DATA_WIDTH-1:0]  aluOut;
    logic                   eq;
    logic [ADDR_WIDTH-1:0]  nextPC;
    logic [ADDR_WIDTH-1:0]  branchPC;
    logic [ADDR_WIDTH-1:0]  incPC;
    
    instr_mem #(
        .ADDR_WIDTH(ADDR_WIDTH),
        .INSTR_WIDTH(INSTR_WIDTH)
    ) imem (
        .pc (pc),
        .instr (instr)
    );

    sign_extend sign_ext (
        .instruction(instr),
        .immSrc(immSrc),
        .imm_ext(immOp)
    );

    control_unit ctrl_unit (
        .opcode (instr[6:0]),
        .funct3 (instr[14:12]),
        .reg_write (regWrite),
        .eq (eq),
        .alu_src (aluSrc),
        .branch (pcSrc),
        .alu_op (aluCtrl),
        .immSrc (immSrc),
        .PCsrc(pcSrc)
    );

    RegFile #(
        .DATA_WIDTH(DATA_WIDTH),
        .REG_DATA_WIDTH(REG_DATA_WIDTH)
    ) RegFile (
        .clk (clk),
        .rs1 (instr[19:15]),
        .rs2 (instr[24:20]),
        .rd (instr[11:7]),
        .RegWrite (regWrite),
        .ALUout (aluOut),
        .a0 (a0),
        .ALUop1 (aluOp1),
        .regOp2 (regOp2)
    );

    mux regFileMux (
        .ImmOp (immOp),
        .regOp2 (regOp2),
        .ALUsrc (aluSrc),
        .ALUop2 (aluOp2)
    );

    ALU regFileALU (
        .ALUop1 (aluOp1),
        .ALUop2 (aluOp2),
        .ALUctrl (aluCtrl),
        .ALUout (aluOut),
        .EQ (eq)
    );

    PCReg PCReg (
        .clk (clk),
        .rst (rst),
        .PC (pc),
        .next_PC (nextPC)
    );

    mux2 pcMux (
        .inc_PC (incPC),
        .branch_PC (branchPC),
        .PCsrc (pcSrc),
        .next_PC (nextPC)
    );

    always_comb begin
        incPC = pc + OFFSET;
        branchPC = pc + immOp[15:0];
    end

endmodule

main/tb/waveform.vcd
$version Generated by VerilatedVcd $end
$date Thu Nov 28 04:29:23 2024 $end
$timescale 1ps $end

 $scope module TOP $end
  $var wire 32 _ a0 [31:0] $end
  $var wire  1 ] clk $end
  $var wire  1 ^ rst $end
  $scope module top $end
   $var wire 32 a ADDR_WIDTH [31:0] $end
   $var wire 32 ` DATA_WIDTH [31:0] $end
   $var wire 32 ` INSTR_WIDTH [31:0] $end
   $var wire 32 c OFFSET [31:0] $end
   $var wire 32 b REG_DATA_WIDTH [31:0] $end
   $var wire 32 _ a0 [31:0] $end
   $var wire  3 ' aluCtrl [2:0] $end
   $var wire 32 + aluOp1 [31:0] $end
   $var wire 32 , aluOp2 [31:0] $end
   $var wire 32 . aluOut [31:0] $end
   $var wire  1 ( aluSrc $end
   $var wire 16 1 branchPC [15:0] $end
   $var wire  1 ] clk $end
   $var wire  1 / eq $end
   $var wire 32 % immOp [31:0] $end
   $var wire  1 ) immSrc $end
   $var wire 16 2 incPC [15:0] $end
   $var wire 32 $ instr [31:0] $end
   $var wire 16 0 nextPC [15:0] $end
   $var wire 16 # pc [15:0] $end
   $var wire  1 * pcSrc $end
   $var wire 32 - regOp2 [31:0] $end
   $var wire  1 & regWrite $end
   $var wire  1 ^ rst $end
   $scope module PCReg $end
    $var wire 32 a DATA_WIDTH [31:0] $end
    $var wire 16 # PC [15:0] $end
    $var wire  1 ] clk $end
    $var wire 16 0 next_PC [15:0] $end
    $var wire  1 ^ rst $end
   $upscope $end
   $scope module RegFile $end
    $var wire 32 + ALUop1 [31:0] $end
    $var wire 32 . ALUout [31:0] $end
    $var wire 32 ` DATA_WIDTH [31:0] $end
    $var wire 32 b REG_DATA_WIDTH [31:0] $end
    $var wire  1 & RegWrite $end
    $var wire 32 _ a0 [31:0] $end
    $var wire  1 ] clk $end
    $var wire  5 5 rd [4:0] $end
    $var wire 32 - regOp2 [31:0] $end
    $var wire 32 6 rom_array[0] [31:0] $end
    $var wire 32 @ rom_array[10] [31:0] $end
    $var wire 32 A rom_array[11] [31:0] $end
    $var wire 32 B rom_array[12] [31:0] $end
    $var wire 32 C rom_array[13] [31:0] $end
    $var wire 32 D rom_array[14] [31:0] $end
    $var wire 32 E rom_array[15] [31:0] $end
    $var wire 32 F rom_array[16] [31:0] $end
    $var wire 32 G rom_array[17] [31:0] $end
    $var wire 32 H rom_array[18] [31:0] $end
    $var wire 32 I rom_array[19] [31:0] $end
    $var wire 32 7 rom_array[1] [31:0] $end
    $var wire 32 J rom_array[20] [31:0] $end
    $var wire 32 K rom_array[21] [31:0] $end
    $var wire 32 L rom_array[22] [31:0] $end
    $var wire 32 M rom_array[23] [31:0] $end
    $var wire 32 N rom_array[24] [31:0] $end
    $var wire 32 O rom_array[25] [31:0] $end
    $var wire 32 P rom_array[26] [31:0] $end
    $var wire 32 Q rom_array[27] [31:0] $end
    $var wire 32 R rom_array[28] [31:0] $end
    $var wire 32 S rom_array[29] [31:0] $end
    $var wire 32 8 rom_array[2] [31:0] $end
    $var wire 32 T rom_array[30] [31:0] $end
    $var wire 32 U rom_array[31] [31:0] $end
    $var wire 32 9 rom_array[3] [31:0] $end
    $var wire 32 : rom_array[4] [31:0] $end
    $var wire 32 ; rom_array[5] [31:0] $end
    $var wire 32 < rom_array[6] [31:0] $end
    $var wire 32 = rom_array[7] [31:0] $end
    $var wire 32 > rom_array[8] [31:0] $end
    $var wire 32 ? rom_array[9] [31:0] $end
    $var wire  5 3 rs1 [4:0] $end
    $var wire  5 4 rs2 [4:0] $end
   $upscope $end
   $scope module ctrl_unit $end
    $var wire  1 * PCsrc $end
    $var wire  3 ' alu_op [2:0] $end
    $var wire  1 ( alu_src $end
    $var wire  1 * branch $end
    $var wire  1 / eq $end
    $var wire  3 W funct3 [2:0] $end
    $var wire  1 ) immSrc $end
    $var wire  7 V opcode [6:0] $end
    $var wire  1 & reg_write $end
   $upscope $end
   $scope module imem $end
    $var wire 32 a ADDR_WIDTH [31:0] $end
    $var wire 32 ` INSTR_WIDTH [31:0] $end
    $var wire 32 $ instr [31:0] $end
    $var wire 16 # pc [15:0] $end
   $upscope $end
   $scope module pcMux $end
    $var wire 32 a ADDR_WIDTH [31:0] $end
    $var wire  1 * PCsrc $end
    $var wire 16 1 branch_PC [15:0] $end
    $var wire 16 2 inc_PC [15:0] $end
    $var wire 16 0 next_PC [15:0] $end
   $upscope $end
   $scope module regFileALU $end
    $var wire  3 ' ALUctrl [2:0] $end
    $var wire 32 + ALUop1 [31:0] $end
    $var wire 32 , ALUop2 [31:0] $end
    $var wire 32 . ALUout [31:0] $end
    $var wire 32 ` DATA_WIDTH [31:0] $end
    $var wire  1 / EQ $end
    $var wire 32 X addi [31:0] $end
    $var wire 32 Z andA [31:0] $end
    $var wire  1 \ match $end
    $var wire 32 [ orA [31:0] $end
    $var wire 32 Y sub [31:0] $end
   $upscope $end
   $scope module regFileMux $end
    $var wire 32 , ALUop2 [31:0] $end
    $var wire  1 ( ALUsrc $end
    $var wire 32 ` DATA_WIDTH [31:0] $end
    $var wire 32 % ImmOp [31:0] $end
    $var wire 32 - regOp2 [31:0] $end
   $upscope $end
   $scope module sign_ext $end
    $var wire  1 ) immSrc $end
    $var wire 32 % imm_ext [31:0] $end
    $var wire 32 $ instruction [31:0] $end
   $upscope $end
  $upscope $end
 $upscope $end
$enddefinitions $end


#0
b0000000000000000 #
b00000000000000000000000000010011 $
b00000000000000000000000000000000 %
1&
b000 '
1(
0)
0*
b00000000000000000000000000000000 +
b00000000000000000000000000000000 ,
b00000000000000000000000000000000 -
b00000000000000000000000000000000 .
0/
b0000000000000100 0
b0000000000000000 1
b0000000000000100 2
b00000 3
b00000 4
b00000 5
b00000000000000000000000000000000 6
b00000000000000000000000000000001 7
b00000000000000000000000000000010 8
b00000000000000000000000000000011 9
b00000000000000000000000000000100 :
b00000000000000000000000000000101 ;
b00000000000000000000000000000110 <
b00000000000000000000000000000111 =
b00000000000000000000000000001000 >
b00000000000000000000000000001001 ?
b00000000000000000000000000010000 @
b00000000000000000000000000010001 A
b00000000000000000000000000010010 B
b00000000000000000000000000010011 C
b00000000000000000000000000010100 D
b00000000000000000000000000010101 E
b00000000000000000000000000010110 F
b00000000000000000000000000010111 G
b00000000000000000000000000011000 H
b00000000000000000000000000011001 I
b00000000000000000000000000100000 J
b00000000000000000000000000100001 K
b00000000000000000000000000100010 L
b00000000000000000000000000100011 M
b00000000000000000000000000100100 N
b00000000000000000000000000100101 O
b00000000000000000000000000100110 P
b00000000000000000000000000100111 Q
b00000000000000000000000000101000 R
b00000000000000000000000000101001 S
b00000000000000000000000000110000 T
b00000000000000000000000000110001 U
b0010011 V
b000 W
b00000000000000000000000000000000 X
b00000000000000000000000000000000 Y
b00000000000000000000000000000000 Z
b00000000000000000000000000000000 [
0\
1]
0^
b00000000000000000000000000000000 _
b00000000000000000000000000100000 `
b00000000000000000000000000010000 a
b00000000000000000000000000000101 b
b00000000000000000000000000000100 c
#1
0]
#2
b0000000000000100 #
b0000000000001000 0
b0000000000000100 1
b0000000000001000 2
1]
#3
0]
#4
b0000000000001000 #
b00000000000000000000000010010011 $
b0000000000001100 0
b0000000000001000 1
b0000000000001100 2
b00001 5
1]
b00000000000000000000000000000001 _
#5
0]
#6
b0000000000001100 #
b00000000000000000000000000010011 $
b0000000000010000 0
b0000000000001100 1
b0000000000010000 2
b00000 5
b00000000000000000000000000000000 7
1]
b00000000000000000000000000000000 _
#7
0]
#8
b0000000000010000 #
b00000000000000000000000010010011 $
b0000000000010100 0
b0000000000010000 1
b0000000000010100 2
b00001 5
1]
#9
0]
#10
b0000000000010100 #
b00000000000000000000000011100011 $
b00000000000000000000100000000000 %
0&
b001 '
0(
1)
b0000000000011000 0
b0000100000010100 1
b0000000000011000 2
b1100011 V
1]
#11
0]
#12
b0000000000011000 #
b0000000000011100 0
b0000100000011000 1
b0000000000011100 2
1]
#13
0]
#14
b0000000000011100 #
b00000000000000000000000000000000 $
b00000000000000000000000000000000 %
b000 '
0)
b0000000000100000 0
b0000000000011100 1
b0000000000100000 2
b00000 5
b0000000 V
1]
#15
0]
#16
b0000000000100000 #
b0000000000100100 0
b0000000000100000 1
b0000000000100100 2
1]
#17
0]
#18
b0000000000100100 #
b0000000000101000 0
b0000000000100100 1
b0000000000101000 2
1]
#19
0]
#20
b0000000000101000 #
b0000000000101100 0
b0000000000101000 1
b0000000000101100 2
1]
#21
0]
#22
b0000000000101100 #
b0000000000110000 0
b0000000000101100 1
b0000000000110000 2
1]
#23
0]
#24
b0000000000110000 #
b0000000000110100 0
b0000000000110000 1
b0000000000110100 2
1]
#25
0]
#26
b0000000000110100 #
b0000000000111000 0
b0000000000110100 1
b0000000000111000 2
1]
#27
0]
#28
b0000000000111000 #
b0000000000111100 0
b0000000000111000 1
b0000000000111100 2
1]
#29
0]
#30
b0000000000111100 #
b0000000001000000 0
b0000000000111100 1
b0000000001000000 2
1]
#31
0]
#32
b0000000001000000 #
b0000000001000100 0
b0000000001000000 1
b0000000001000100 2
1]
#33
0]
#34
b0000000001000100 #
b0000000001001000 0
b0000000001000100 1
b0000000001001000 2
1]
#35
0]
#36
b0000000001001000 #
b0000000001001100 0
b0000000001001000 1
b0000000001001100 2
1]
#37
0]
#38
b0000000001001100 #
b0000000001010000 0
b0000000001001100 1
b0000000001010000 2
1]
#39
0]
#40
b0000000001010000 #
b0000000001010100 0
b0000000001010000 1
b0000000001010100 2
1]
#41
0]
#42
b0000000001010100 #
b0000000001011000 0
b0000000001010100 1
b0000000001011000 2
1]
#43
0]
#44
b0000000001011000 #
b0000000001011100 0
b0000000001011000 1
b0000000001011100 2
1]
#45
0]
#46
b0000000001011100 #
b0000000001100000 0
b0000000001011100 1
b0000000001100000 2
1]
#47
0]
#48
b0000000001100000 #
b0000000001100100 0
b0000000001100000 1
b0000000001100100 2
1]
#49
0]
#50
b0000000001100100 #
b0000000001101000 0
b0000000001100100 1
b0000000001101000 2
1]
#51
0]
#52
b0000000001101000 #
b0000000001101100 0
b0000000001101000 1
b0000000001101100 2
1]
#53
0]
#54
b0000000001101100 #
b0000000001110000 0
b0000000001101100 1
b0000000001110000 2
1]
#55
0]
#56
b0000000001110000 #
b0000000001110100 0
b0000000001110000 1
b0000000001110100 2
1]
#57
0]
#58
b0000000001110100 #
b0000000001111000 0
b0000000001110100 1
b0000000001111000 2
1]
#59
0]
#60
b0000000001111000 #
b0000000001111100 0
b0000000001111000 1
b0000000001111100 2
1]
#61
0]
#62
b0000000001111100 #
b0000000010000000 0
b0000000001111100 1
b0000000010000000 2
1]
#63
0]
#64
b0000000010000000 #
b0000000010000100 0
b0000000010000000 1
b0000000010000100 2
1]
#65
0]
#66
b0000000010000100 #
b0000000010001000 0
b0000000010000100 1
b0000000010001000 2
1]
#67
0]
#68
b0000000010001000 #
b0000000010001100 0
b0000000010001000 1
b0000000010001100 2
1]
#69
0]
#70
b0000000010001100 #
b0000000010010000 0
b0000000010001100 1
b0000000010010000 2
1]
#71
0]
#72
b0000000010010000 #
b0000000010010100 0
b0000000010010000 1
b0000000010010100 2
1]
#73
0]
#74
b0000000010010100 #
b0000000010011000 0
b0000000010010100 1
b0000000010011000 2
1]
#75
0]
#76
b0000000010011000 #
b0000000010011100 0
b0000000010011000 1
b0000000010011100 2
1]
#77
0]
#78
b0000000010011100 #
b0000000010100000 0
b0000000010011100 1
b0000000010100000 2
1]
#79
0]
#80
b0000000010100000 #
b0000000010100100 0
b0000000010100000 1
b0000000010100100 2
1]
#81
0]
#82
b0000000010100100 #
b0000000010101000 0
b0000000010100100 1
b0000000010101000 2
1]
#83
0]
#84
b0000000010101000 #
b0000000010101100 0
b0000000010101000 1
b0000000010101100 2
1]
#85
0]
#86
b0000000010101100 #
b0000000010110000 0
b0000000010101100 1
b0000000010110000 2
1]
#87
0]
#88
b0000000010110000 #
b0000000010110100 0
b0000000010110000 1
b0000000010110100 2
1]
#89
0]
#90
b0000000010110100 #
b0000000010111000 0
b0000000010110100 1
b0000000010111000 2
1]
#91
0]
#92
b0000000010111000 #
b0000000010111100 0
b0000000010111000 1
b0000000010111100 2
1]
#93
0]
#94
b0000000010111100 #
b0000000011000000 0
b0000000010111100 1
b0000000011000000 2
1]
#95
0]
#96
b0000000011000000 #
b0000000011000100 0
b0000000011000000 1
b0000000011000100 2
1]
#97
0]
#98
b0000000011000100 #
b0000000011001000 0
b0000000011000100 1
b0000000011001000 2
1]
#99
0]
#100
b0000000011001000 #
b0000000011001100 0
b0000000011001000 1
b0000000011001100 2
1]
#101
0]
#102
b0000000011001100 #
b0000000011010000 0
b0000000011001100 1
b0000000011010000 2
1]
#103
0]
#104
b0000000011010000 #
b0000000011010100 0
b0000000011010000 1
b0000000011010100 2
1]
#105
0]
#106
b0000000011010100 #
b0000000011011000 0
b0000000011010100 1
b0000000011011000 2
1]
#107
0]
#108
b0000000011011000 #
b0000000011011100 0
b0000000011011000 1
b0000000011011100 2
1]
#109
0]
#110
b0000000011011100 #
b0000000011100000 0
b0000000011011100 1
b0000000011100000 2
1]
#111
0]
#112
b0000000011100000 #
b0000000011100100 0
b0000000011100000 1
b0000000011100100 2
1]
#113
0]
#114
b0000000011100100 #
b0000000011101000 0
b0000000011100100 1
b0000000011101000 2
1]
#115
0]
#116
b0000000011101000 #
b0000000011101100 0
b0000000011101000 1
b0000000011101100 2
1]
#117
0]
#118
b0000000011101100 #
b0000000011110000 0
b0000000011101100 1
b0000000011110000 2
1]
#119
0]
#120
b0000000011110000 #
b0000000011110100 0
b0000000011110000 1
b0000000011110100 2
1]
#121
0]
#122
b0000000011110100 #
b0000000011111000 0
b0000000011110100 1
b0000000011111000 2
1]
#123
0]
#124
b0000000011111000 #
b0000000011111100 0
b0000000011111000 1
b0000000011111100 2
1]
#125
0]
#126
b0000000011111100 #
b0000000100000000 0
b0000000011111100 1
b0000000100000000 2
1]
#127
0]
#128
b0000000100000000 #
b0000000100000100 0
b0000000100000000 1
b0000000100000100 2
1]
#129
0]
#130
b0000000100000100 #
b0000000100001000 0
b0000000100000100 1
b0000000100001000 2
1]
#131
0]
#132
b0000000100001000 #
b0000000100001100 0
b0000000100001000 1
b0000000100001100 2
1]
#133
0]
#134
b0000000100001100 #
b0000000100010000 0
b0000000100001100 1
b0000000100010000 2
1]
#135
0]
#136
b0000000100010000 #
b0000000100010100 0
b0000000100010000 1
b0000000100010100 2
1]
#137
0]
#138
b0000000100010100 #
b0000000100011000 0
b0000000100010100 1
b0000000100011000 2
1]
#139
0]
#140
b0000000100011000 #
b0000000100011100 0
b0000000100011000 1
b0000000100011100 2
1]
#141
0]
#142
b0000000100011100 #
b0000000100100000 0
b0000000100011100 1
b0000000100100000 2
1]
#143
0]
#144
b0000000100100000 #
b0000000100100100 0
b0000000100100000 1
b0000000100100100 2
1]
#145
0]
#146
b0000000100100100 #
b0000000100101000 0
b0000000100100100 1
b0000000100101000 2
1]
#147
0]
#148
b0000000100101000 #
b0000000100101100 0
b0000000100101000 1
b0000000100101100 2
1]
#149
0]
#150
b0000000100101100 #
b0000000100110000 0
b0000000100101100 1
b0000000100110000 2
1]
#151
0]
#152
b0000000100110000 #
b0000000100110100 0
b0000000100110000 1
b0000000100110100 2
1]
#153
0]
#154
b0000000100110100 #
b0000000100111000 0
b0000000100110100 1
b0000000100111000 2
1]
#155
0]
#156
b0000000100111000 #
b0000000100111100 0
b0000000100111000 1
b0000000100111100 2
1]
#157
0]
#158
b0000000100111100 #
b0000000101000000 0
b0000000100111100 1
b0000000101000000 2
1]
#159
0]
#160
b0000000101000000 #
b0000000101000100 0
b0000000101000000 1
b0000000101000100 2
1]
#161
0]
#162
b0000000101000100 #
b0000000101001000 0
b0000000101000100 1
b0000000101001000 2
1]
#163
0]
#164
b0000000101001000 #
b0000000101001100 0
b0000000101001000 1
b0000000101001100 2
1]
#165
0]
#166
b0000000101001100 #
b0000000101010000 0
b0000000101001100 1
b0000000101010000 2
1]
#167
0]
#168
b0000000101010000 #
b0000000101010100 0
b0000000101010000 1
b0000000101010100 2
1]
#169
0]
#170
b0000000101010100 #
b0000000101011000 0
b0000000101010100 1
b0000000101011000 2
1]
#171
0]
#172
b0000000101011000 #
b0000000101011100 0
b0000000101011000 1
b0000000101011100 2
1]
#173
0]
#174
b0000000101011100 #
b0000000101100000 0
b0000000101011100 1
b0000000101100000 2
1]
#175
0]
#176
b0000000101100000 #
b0000000101100100 0
b0000000101100000 1
b0000000101100100 2
1]
#177
0]
#178
b0000000101100100 #
b0000000101101000 0
b0000000101100100 1
b0000000101101000 2
1]
#179
0]
#180
b0000000101101000 #
b0000000101101100 0
b0000000101101000 1
b0000000101101100 2
1]
#181
0]
#182
b0000000101101100 #
b0000000101110000 0
b0000000101101100 1
b0000000101110000 2
1]
#183
0]
#184
b0000000101110000 #
b0000000101110100 0
b0000000101110000 1
b0000000101110100 2
1]
#185
0]
#186
b0000000101110100 #
b0000000101111000 0
b0000000101110100 1
b0000000101111000 2
1]
#187
0]
#188
b0000000101111000 #
b0000000101111100 0
b0000000101111000 1
b0000000101111100 2
1]
#189
0]
#190
b0000000101111100 #
b0000000110000000 0
b0000000101111100 1
b0000000110000000 2
1]
#191
0]
#192
b0000000110000000 #
b0000000110000100 0
b0000000110000000 1
b0000000110000100 2
1]
#193
0]
#194
b0000000110000100 #
b0000000110001000 0
b0000000110000100 1
b0000000110001000 2
1]
#195
0]
#196
b0000000110001000 #
b0000000110001100 0
b0000000110001000 1
b0000000110001100 2
1]
#197
0]
#198
b0000000110001100 #
b0000000110010000 0
b0000000110001100 1
b0000000110010000 2
1]
#199
0]
#200
b0000000110010000 #
b0000000110010100 0
b0000000110010000 1
b0000000110010100 2
1]
#201
0]
#202
b0000000110010100 #
b0000000110011000 0
b0000000110010100 1
b0000000110011000 2
1]
#203
0]
#204
b0000000110011000 #
b0000000110011100 0
b0000000110011000 1
b0000000110011100 2
1]
#205
0]
#206
b0000000110011100 #
b0000000110100000 0
b0000000110011100 1
b0000000110100000 2
1]
#207
0]
#208
b0000000110100000 #
b0000000110100100 0
b0000000110100000 1
b0000000110100100 2
1]
#209
0]
#210
b0000000110100100 #
b0000000110101000 0
b0000000110100100 1
b0000000110101000 2
1]
#211
0]
#212
b0000000110101000 #
b0000000110101100 0
b0000000110101000 1
b0000000110101100 2
1]
#213
0]
#214
b0000000110101100 #
b0000000110110000 0
b0000000110101100 1
b0000000110110000 2
1]
#215
0]
#216
b0000000110110000 #
b0000000110110100 0
b0000000110110000 1
b0000000110110100 2
1]
#217
0]
#218
b0000000110110100 #
b0000000110111000 0
b0000000110110100 1
b0000000110111000 2
1]
#219
0]
#220
b0000000110111000 #
b0000000110111100 0
b0000000110111000 1
b0000000110111100 2
1]
#221
0]
#222
b0000000110111100 #
b0000000111000000 0
b0000000110111100 1
b0000000111000000 2
1]
#223
0]
#224
b0000000111000000 #
b0000000111000100 0
b0000000111000000 1
b0000000111000100 2
1]
#225
0]
#226
b0000000111000100 #
b0000000111001000 0
b0000000111000100 1
b0000000111001000 2
1]
#227
0]
#228
b0000000111001000 #
b0000000111001100 0
b0000000111001000 1
b0000000111001100 2
1]
#229
0]
#230
b0000000111001100 #
b0000000111010000 0
b0000000111001100 1
b0000000111010000 2
1]
#231
0]
#232
b0000000111010000 #
b0000000111010100 0
b0000000111010000 1
b0000000111010100 2
1]
#233
0]
#234
b0000000111010100 #
b0000000111011000 0
b0000000111010100 1
b0000000111011000 2
1]
#235
0]
#236
b0000000111011000 #
b0000000111011100 0
b0000000111011000 1
b0000000111011100 2
1]
#237
0]
#238
b0000000111011100 #
b0000000111100000 0
b0000000111011100 1
b0000000111100000 2
1]
#239
0]
#240
b0000000111100000 #
b0000000111100100 0
b0000000111100000 1
b0000000111100100 2
1]
#241
0]
#242
b0000000111100100 #
b0000000111101000 0
b0000000111100100 1
b0000000111101000 2
1]
#243
0]
#244
b0000000111101000 #
b0000000111101100 0
b0000000111101000 1
b0000000111101100 2
1]
#245
0]
#246
b0000000111101100 #
b0000000111110000 0
b0000000111101100 1
b0000000111110000 2
1]
#247
0]
#248
b0000000111110000 #
b0000000111110100 0
b0000000111110000 1
b0000000111110100 2
1]
#249
0]
#250
b0000000111110100 #
b0000000111111000 0
b0000000111110100 1
b0000000111111000 2
1]
#251
0]
#252
b0000000111111000 #
b0000000111111100 0
b0000000111111000 1
b0000000111111100 2
1]
#253
0]
#254
b0000000111111100 #
b0000001000000000 0
b0000000111111100 1
b0000001000000000 2
1]
#255
0]
#256
b0000001000000000 #
b0000001000000100 0
b0000001000000000 1
b0000001000000100 2
1]
#257
0]
#258
b0000001000000100 #
b0000001000001000 0
b0000001000000100 1
b0000001000001000 2
1]
#259
0]
#260
b0000001000001000 #
b0000001000001100 0
b0000001000001000 1
b0000001000001100 2
1]
#261
0]
#262
b0000001000001100 #
b0000001000010000 0
b0000001000001100 1
b0000001000010000 2
1]
#263
0]
#264
b0000001000010000 #
b0000001000010100 0
b0000001000010000 1
b0000001000010100 2
1]
#265
0]
#266
b0000001000010100 #
b0000001000011000 0
b0000001000010100 1
b0000001000011000 2
1]
#267
0]
#268
b0000001000011000 #
b0000001000011100 0
b0000001000011000 1
b0000001000011100 2
1]
#269
0]
#270
b0000001000011100 #
b0000001000100000 0
b0000001000011100 1
b0000001000100000 2
1]
#271
0]
#272
b0000001000100000 #
b0000001000100100 0
b0000001000100000 1
b0000001000100100 2
1]
#273
0]
#274
b0000001000100100 #
b0000001000101000 0
b0000001000100100 1
b0000001000101000 2
1]
#275
0]
#276
b0000001000101000 #
b0000001000101100 0
b0000001000101000 1
b0000001000101100 2
1]
#277
0]
#278
b0000001000101100 #
b0000001000110000 0
b0000001000101100 1
b0000001000110000 2
1]
#279
0]
#280
b0000001000110000 #
b0000001000110100 0
b0000001000110000 1
b0000001000110100 2
1]
#281
0]
#282
b0000001000110100 #
b0000001000111000 0
b0000001000110100 1
b0000001000111000 2
1]
#283
0]
#284
b0000001000111000 #
b0000001000111100 0
b0000001000111000 1
b0000001000111100 2
1]
#285
0]
#286
b0000001000111100 #
b0000001001000000 0
b0000001000111100 1
b0000001001000000 2
1]
